CHANGELOG.txt
LICENCE.txt
MANIFEST.in
README.txt
setup.py
BloodDroplet/__init__.py
BloodDroplet/code.py
Blood_Droplet.egg-info/PKG-INFO
Blood_Droplet.egg-info/SOURCES.txt
Blood_Droplet.egg-info/dependency_links.txt
Blood_Droplet.egg-info/top_level.txt