Metadata-Version: 2.1
Name: Blood-Droplet
Version: 0.0.0
Summary: Image Processing, Preprocessing Module, Extract Blood Droplet, Masking Image
Home-page: https://github.com/krisskad/BloodDroplet
Author: Krishna Kadam
Author-email: krisskad0@gmail.com
Maintainer: Krishna kadam
License: MIT License
Platform: UNKNOWN
Classifier: Intended Audience :: Developers
Classifier: License :: OSI Approved :: MIT License
Classifier: Operating System :: OS Independent
Classifier: Programming Language :: Python
Classifier: Programming Language :: Python :: 3
Classifier: Topic :: Software Development :: Libraries
Requires: numpy
Requires: opencv
